bigselfies/__init__.py
bigselfies-0.0.1.dist-info/LICENSE.txt
bigselfies-0.0.1.dist-info/METADATA
bigselfies-0.0.1.dist-info/WHEEL
bigselfies-0.0.1.dist-info/top_level.txt
bigselfies-0.0.1.dist-info/RECORD
