Metadata-Version: 2.1
Name: bigselfies
Version: 0.0.1
Summary: Big things
Home-page: https://github.com/dylanwal/bigselfies
Author: Dylan Walsh
License: BSD
Platform: any
Classifier: License :: OSI Approved :: BSD License
Classifier: Programming Language :: Python :: 3
Classifier: Programming Language :: Python :: 3 :: Only
Classifier: Programming Language :: Python :: 3.10
Requires-Python: >=3.9
License-File: LICENSE.txt
